{
    "commentThread": [
        {
            "id": "5208732208",
            "user": "disqus_BBUm5xfcIE",
            "date": "3 days ago",
            "timestamp": "NA",
            "commentText": "Porque é que é mau?!... Vocês deviam ter vergonha de vir com esses discursos de moralidade tão baixa!... <br/>Que fizeram durante este anos todos senão fazer germinar em nós a vontade de mudar o regime corruto que nos governa?!... Que querem que o povo faça senão ansiar por gente honesta ao leme do poder?!...<br/>Estamos fartos de todos vós e já temos nojo de ver sempre os mesmos ao longo destes quarenta e tal anos!...<br/>Queremos mudar !!!...<br/>O Chega é a nossa esperança neste regime corrupto!...<br/>Força André Ventura!... Vamos mudar o país e dar dignidade à Nação, tão maltratada por esta escumalha que parasita o erário público!...<br/>Estamos contigo, porque queremos gente competente e honesta ao leme do país!!!... Acreditamos em ti e vamos ganhar esta esquerda que quer afunadar o país!...<br/>Força!!!...",
            "likes": 1,
            "hasReplies": true,
            "numberOfReplies": 8,
            "replies": [
                {
                    "id": "5208893732",
                    "user": "disqus_q9dul5DrtD",
                    "date": "3 days ago",
                    "timestamp": "NA",
                    "commentText": "O Chega não é esperança para nada, pelo contrário.<br/>Um partido que não respeita as pessoas, e as avalia pela cor, religião, sexo,,................não faz falta em democracia nenhuma do Mundo.",
                    "likes": 0,
                    "hasReplies": true,
                    "numberOfReplies": 7,
                    "replies": [
                        {
                            "id": "5208918749",
                            "user": "disqus_BBUm5xfcIE",
                            "date": "3 days ago",
                            "timestamp": "NA",
                            "commentText": "Deixemo-nos de preconceitos e sejamos realistas!...  Não respeita quem?!... Os ciganos?!...  Os pretos?!... Onde viu isso?!...<br/>O Chega não é contra ninguém, apenas contra os que não respeitam as leis da Nação, vivem do roubo e querem direitos sem qualquer contrapartida!!!... Isso é mau?!...<br/>Então que venha o Chega e meta mais dez ou 15 deputados no parlamento !!!... O Chega vai ser uma força neste país de corruptos e arranjistas!!!... <br/>Força André Ventura!...",
                            "likes": 1,
                            "hasReplies": true,
                            "numberOfReplies": 6,
                            "replies": [
                                {
                                    "id": "5209059955",
                                    "user": "disqus_q9dul5DrtD",
                                    "date": "3 days ago",
                                    "timestamp": "NA",
                                    "commentText": "Como afirmei partidos como o Chega não fazem falta nenhuma, em nenhuma democracia do Mundo.",
                                    "likes": 0,
                                    "hasReplies": true,
                                    "numberOfReplies": 5,
                                    "replies": [
                                        {
                                            "id": "5209082532",
                                            "user": "disqus_BBUm5xfcIE",
                                            "date": "3 days ago",
                                            "timestamp": "NA",
                                            "commentText": "Penso o mesmo em relação ao PC e BE.  Aliás, não entendo como não se extinguiu ainda em Portugal e Espanha, ainda que tenham sido reduzidos à quase nulidade!... Nos países civilizados já nem se fala no PC...",
                                            "likes": 0,
                                            "hasReplies": true,
                                            "numberOfReplies": 4,
                                            "replies": [
                                                {
                                                    "id": "5209564905",
                                                    "user": "disqus_q9dul5DrtD",
                                                    "date": "3 days ago",
                                                    "timestamp": "NA",
                                                    "commentText": "Engana-se PC e BE existe em todos os Países, com outros nomes, com mais, ou menos expressão.",
                                                    "likes": 0,
                                                    "hasReplies": true,
                                                    "numberOfReplies": 3,
                                                    "replies": [
                                                        {
                                                            "id": "5209579225",
                                                            "user": "disqus_BBUm5xfcIE",
                                                            "date": "2 days ago",
                                                            "timestamp": "NA",
                                                            "commentText": "Engana-se. Estão na sua natural extinção!... As ditaduras comunistas, sanguinárias, estão em absoluta extinção!!!...",
                                                            "likes": 0,
                                                            "hasReplies": true,
                                                            "numberOfReplies": 2,
                                                            "replies": [
                                                                {
                                                                    "id": "5209627210",
                                                                    "user": "disqus_q9dul5DrtD",
                                                                    "date": "2 days ago",
                                                                    "timestamp": "NA",
                                                                    "commentText": "Ditaduras sim, mas há alguns partidos da extrema direita que as querem repor, mas eu espero que nunca mais haja ditadura em Portugal, seja de esquerda, seja de direita.",
                                                                    "likes": 0,
                                                                    "hasReplies": true,
                                                                    "numberOfReplies": 1,
                                                                    "replies": [
                                                                        {
                                                                            "id": "5209885838",
                                                                            "user": "disqus_BBUm5xfcIE",
                                                                            "date": "2 days ago",
                                                                            "timestamp": "NA",
                                                                            "commentText": "Pois... vivemos actualmente a ditadura da partidocracia corrupta!... Esta é que eu não quero e luto para que seja extinta!!!... Apareça alguém que prometa acabar com isto!!!...<br/>Este regime corrupto, com milhares de parasitas, é que não!!!...",
                                                                            "likes": 0,
                                                                            "hasReplies": false,
                                                                            "numberOfReplies": 0,
                                                                            "replies": []
                                                                        }
                                                                    ]
                                                                }
                                                            ]
                                                        }
                                                    ]
                                                }
                                            ]
                                        }
                                    ]
                                }
                            ]
                        }
                    ]
                }
            ]
        },
        {
            "id": "5207755434",
            "user": "comunistaasrio",
            "date": "4 days ago",
            "timestamp": "NA",
            "commentText": "Se algum dia precisares de apoio para formar governo, devias ir bater à porta da Ana Gomes.",
            "likes": 1,
            "hasReplies": true,
            "numberOfReplies": 5,
            "replies": [
                {
                    "id": "5209078003",
                    "user": "disqus_0N81tDtXMQmatita",
                    "date": "3 days ago",
                    "timestamp": "NA",
                    "commentText": "Ana Gomes: “A grande divisão, no PS e fora, é entre quem é sério e quem não é”",
                    "likes": 0,
                    "hasReplies": true,
                    "numberOfReplies": 4,
                    "replies": [
                        {
                            "id": "5209081455",
                            "user": "disqus_q9dul5DrtD",
                            "date": "3 days ago",
                            "timestamp": "NA",
                            "commentText": "Que grande idiotice.",
                            "likes": 0,
                            "hasReplies": true,
                            "numberOfReplies": 3,
                            "replies": [
                                {
                                    "id": "5209089944",
                                    "user": "disqus_0N81tDtXMQmatita",
                                    "date": "3 days ago",
                                    "timestamp": "NA",
                                    "commentText": "Para o PS talvez, não para quem pretende ser sério.",
                                    "likes": 0,
                                    "hasReplies": true,
                                    "numberOfReplies": 2,
                                    "replies": [
                                        {
                                            "id": "5209629778",
                                            "user": "disqus_q9dul5DrtD",
                                            "date": "2 days ago",
                                            "timestamp": "NA",
                                            "commentText": "Na política não há muitas pessoas verdadeiramente sérias.<br/>Mas se fizermos uma análise isenta de certeza que se encontra pessoas menos sérias em outros partidos, do que no PS.<br/>E que tem a Ana Gomes, que até talvez seja quem leva o meu voto, a ver com o serem sérios, ou não.",
                                            "likes": 0,
                                            "hasReplies": true,
                                            "numberOfReplies": 1,
                                            "replies": [
                                                {
                                                    "id": "5209655171",
                                                    "user": "disqus_0N81tDtXMQmatita",
                                                    "date": "2 days ago",
                                                    "timestamp": "NA",
                                                    "commentText": "A prova de que o PS não é sério genuínamente está no combate à corrupção. Apregoa o para fazer o inverso, como ainda recentemente voltou a acontecer.<br/> Porque não aceita a criminalização do enriquecimento ilícito? Porque em cada lei contra, deixa sempre um buraco?<br/>Isto e muito mais arrasta-se desde que esta Constituição foi elaborada. Não me venha falar de seriedade no PS; òbviamente que não têm o exclusivo.",
                                                    "likes": 1,
                                                    "hasReplies": false,
                                                    "numberOfReplies": 0,
                                                    "replies": []
                                                }
                                            ]
                                        }
                                    ]
                                }
                            ]
                        }
                    ]
                }
            ]
        },
        {
            "id": "5207735422",
            "user": "felipeazyral",
            "date": "4 days ago",
            "timestamp": "NA",
            "commentText": "Rui Rio deve esclarecer se faz Oposição ao Desgoverno do PS/PCP, os quais conseguiram aprovar o Orçamento de Estado para 2021 na Assembleia da República ou se se limita a ser Opositor de André Ventura, o qual sustenta o PSD no Governo Regional dos Açores.",
            "likes": 1,
            "hasReplies": true,
            "numberOfReplies": 1,
            "replies": [
                {
                    "id": "5208895336",
                    "user": "disqus_q9dul5DrtD",
                    "date": "3 days ago",
                    "timestamp": "NA",
                    "commentText": "Era muito mau para a maioria dos Portugueses, empresas, mercados,........................ se o OE de 2021 não fosse aprovado.",
                    "likes": 0,
                    "hasReplies": false,
                    "numberOfReplies": 0,
                    "replies": []
                }
            ]
        },
        {
            "id": "5207652329",
            "user": "mariaeugniamrias",
            "date": "4 days ago",
            "timestamp": "NA",
            "commentText": "Mau para o Marcelo.",
            "likes": 0,
            "hasReplies": false,
            "numberOfReplies": 0,
            "replies": []
        },
        {
            "id": "5207646027",
            "user": "brunodecarvalhooprprio",
            "date": "4 days ago",
            "timestamp": "NA",
            "commentText": "Eu acho que estas declarações são más desde logo para o Rui Rio porque parece que só com o Chega a direita poderá chegar ao poder nos próximos tempos ... mas também poderá ser mau para todos os partidos do espectro político tradicional que vivem agarrados ao tacho e têm agora a perspectiva de um político em rotura com o sistema chegar ao poder.",
            "likes": 1,
            "hasReplies": true,
            "numberOfReplies": 1,
            "replies": [
                {
                    "id": "5207695667",
                    "user": "disqus_q9dul5DrtD",
                    "date": "4 days ago",
                    "timestamp": "NA",
                    "commentText": "Qual rotura com o sistema?<br/>Se um dia virtualmente chegasse ao poder e com maioria, tudo seria muito pior que atualmente.",
                    "likes": 0,
                    "hasReplies": false,
                    "numberOfReplies": 0,
                    "replies": []
                }
            ]
        },
        {
            "id": "5207639903",
            "user": "disqus_cBccy1PhIj",
            "date": "4 days ago",
            "timestamp": "NA",
            "commentText": "Mau para Portugal, é sermos o penúltimo da Europa. Só com a Bulgária atrás de nós. <br/>Disto é que o Rui Rio devia falar.",
            "likes": 2,
            "hasReplies": false,
            "numberOfReplies": 0,
            "replies": []
        },
        {
            "id": "5207619752",
            "user": "xicoz",
            "date": "4 days ago",
            "timestamp": "NA",
            "commentText": "\"Será mau se o líder do Chega tiver uma votação grande e expressiva\".......esta frase de rio só pode ter sido tirada do contexto..rui rio nao pensou bem no que disse.....é que alguns milhares de portugueses eleitores  vao  votar no André Ventura ... e... prescindem  que rio lhes  passe um atestado de estupides... e esses eleitores nao esquecem quem os  insulta",
            "likes": 2,
            "hasReplies": true,
            "numberOfReplies": 4,
            "replies": [
                {
                    "id": "5207628988",
                    "user": "disqus_rAIpRKQqXo",
                    "date": "4 days ago",
                    "timestamp": "NA",
                    "commentText": "Se Rui Rio fosse um líder a sério, nunca esqueceria que o adversário é o Costa e o Ventura não deveria passar de um incómodo.",
                    "likes": 1,
                    "hasReplies": true,
                    "numberOfReplies": 3,
                    "replies": [
                        {
                            "id": "5207857353",
                            "user": "disqus_q9dul5DrtD",
                            "date": "4 days ago",
                            "timestamp": "NA",
                            "commentText": "Se Rio quer ser um líder a sério devia preocupar-se em convencer os eleitores com propostas e soluções para os problemas, em vez de dizer mal de tudo só porque sim, e votar contra o OE de 2021 só porque sim.<br/>Mas nada de anormal, os partidos da oposição normalmente são todos assim.",
                            "likes": 0,
                            "hasReplies": true,
                            "numberOfReplies": 2,
                            "replies": [
                                {
                                    "id": "5207862104",
                                    "user": "disqus_rAIpRKQqXo",
                                    "date": "4 days ago",
                                    "timestamp": "NA",
                                    "commentText": "\"Mas nada de anormal, os partidos da oposição normalmente são todos assim.\"<br/>O PS na oposição consegur ser pior.",
                                    "likes": 0,
                                    "hasReplies": true,
                                    "numberOfReplies": 1,
                                    "replies": [
                                        {
                                            "id": "5208822251",
                                            "user": "disqus_q9dul5DrtD",
                                            "date": "3 days ago",
                                            "timestamp": "NA",
                                            "commentText": "Faça uma análise isenta, e vai constatar que não é como afirma, pelo contrário.",
                                            "likes": 0,
                                            "hasReplies": false,
                                            "numberOfReplies": 0,
                                            "replies": []
                                        }
                                    ]
                                }
                            ]
                        }
                    ]
                }
            ]
        },
        {
            "id": "5207614340",
            "user": "aquariustranslucido",
            "date": "4 days ago",
            "timestamp": "NA",
            "commentText": "O Rui Rio, por mais que tente dar nas vistas com opiniões destas, não faz mais que posicionar-se cada vez mais abaixo dos calcanhares do Dr. Francisco Sá Carneiro...<br/>Uma vergonha como nortenho...",
            "likes": 1,
            "hasReplies": false,
            "numberOfReplies": 0,
            "replies": []
        },
        {
            "id": "5207590268",
            "user": "disqus_fi5cXUR6x4",
            "date": "4 days ago",
            "timestamp": "NA",
            "commentText": "RR é uma desgraça como político",
            "likes": 2,
            "hasReplies": false,
            "numberOfReplies": 0,
            "replies": []
        },
        {
            "id": "5207494801",
            "user": "disqus_zNBx4Q8LYg",
            "date": "5 days ago",
            "timestamp": "NA",
            "commentText": "Olha que grande democrata me saiu este, então a democracia não é assim ? mas também não vai longe.",
            "likes": 1,
            "hasReplies": false,
            "numberOfReplies": 0,
            "replies": []
        },
        {
            "id": "5207456035",
            "user": "disqus_HYSkVUqBVn",
            "date": "5 days ago",
            "timestamp": "NA",
            "commentText": "Cheguei a temer, devido ao silêncio da criatura, que tivesse hibernado! Tá visto, a oposição de Rio é feita aos soluços!?!",
            "likes": 3,
            "hasReplies": true,
            "numberOfReplies": 2,
            "replies": [
                {
                    "id": "5207629389",
                    "user": "disqus_rAIpRKQqXo",
                    "date": "4 days ago",
                    "timestamp": "NA",
                    "commentText": "\" a oposição de Rio é feita aos soluços!?!\"<br/>Oposição a quem?",
                    "likes": 1,
                    "hasReplies": false,
                    "numberOfReplies": 0,
                    "replies": []
                },
                {
                    "id": "5207530123",
                    "user": "disqus_q9dul5DrtD",
                    "date": "5 days ago",
                    "timestamp": "NA",
                    "commentText": "Aparece poucas vezes, mas o Rio já parece o Ventura, ou o Líder do CDS, para quem na política vale tudo.<br/>Até acusa o Governo pelas mortes, que há a mais em relação a 2019, que se podem dever a tantos factos, um dos quais a onda de calor que se fez sentir em 2020, o medo, e a ansiedade, medo que levou muitas pessoas a não procurarem ajuda,,,,..................................",
                    "likes": 1,
                    "hasReplies": false,
                    "numberOfReplies": 0,
                    "replies": []
                }
            ]
        },
        {
            "id": "5206969446",
            "user": "disqus_Cn7F4VdGBM",
            "date": "5 days ago",
            "timestamp": "NA",
            "commentText": "nem politico  sabes  ser  , um  dia  destes  podes  precisar  do  chega  para  formar  governo   ...  não  admira  que  o  psd  não vá  adiante  , o  seu  presidente  tem  a astucia  de  uma  barata   .....",
            "likes": 4,
            "hasReplies": false,
            "numberOfReplies": 0,
            "replies": []
        },
        {
            "id": "5206967631",
            "user": "disqus_BzBL8hq9yT",
            "date": "5 days ago",
            "timestamp": "NA",
            "commentText": "E que tal começar fazer oposição? <br/>Vai ser para sempre um adjunto do querido líder antónio costa?",
            "likes": 5,
            "hasReplies": false,
            "numberOfReplies": 0,
            "replies": []
        },
        {
            "id": "5206964507",
            "user": "aquariustranslucido",
            "date": "5 days ago",
            "timestamp": "NA",
            "commentText": "O AV provoca comichão  à esquerda e à direita, por que será!?<br/>Força Ventura...",
            "likes": 7,
            "hasReplies": false,
            "numberOfReplies": 0,
            "replies": []
        },
        {
            "id": "5206948429",
            "user": "disqus_0N81tDtXMQmatita",
            "date": "5 days ago",
            "timestamp": "NA",
            "commentText": "Se é bom ou mau o futuro o dirá. A realidade porém é que AV veio ocupar olugar que o PSD deixou livre por falta de combatividade. A actuação deste partido desde que RR chegou  tem sido confrangedora.",
            "likes": 5,
            "hasReplies": true,
            "numberOfReplies": 2,
            "replies": [
                {
                    "id": "5207070242",
                    "user": "disqus_LerI7mwknD",
                    "date": "5 days ago",
                    "timestamp": "NA",
                    "commentText": "As alternativas a Rui Rio eram piores.",
                    "likes": 1,
                    "hasReplies": true,
                    "numberOfReplies": 1,
                    "replies": [
                        {
                            "id": "5207668708",
                            "user": "aquariustranslucido",
                            "date": "4 days ago",
                            "timestamp": "NA",
                            "commentText": "A diferença é que na direita os piores deitam o partido abaixo, mas na esquerda os mesmos (piores e reles políticos) dão-lhe asas...",
                            "likes": 0,
                            "hasReplies": false,
                            "numberOfReplies": 0,
                            "replies": []
                        }
                    ]
                }
            ]
        },
        {
            "id": "5206936968",
            "user": "felciomafio",
            "date": "5 days ago",
            "timestamp": "NA",
            "commentText": "Vai ser duro...!!",
            "likes": 4,
            "hasReplies": false,
            "numberOfReplies": 0,
            "replies": []
        },
        {
            "id": "5206917468",
            "user": "disqus_UCjuL0mkv1",
            "date": "5 days ago",
            "timestamp": "NA",
            "commentText": "isto é, muito mau para ele...",
            "likes": 2,
            "hasReplies": false,
            "numberOfReplies": 0,
            "replies": []
        },
        {
            "id": "5206909120",
            "user": "bolideirayahoocombr",
            "date": "5 days ago",
            "timestamp": "NA",
            "commentText": "Enquanto Rui Riacho estiver a liderar o PSD, não passará dos 29% de intensão de votos!<br/>Rui Riacho só sabe dar tiros nos pés!! Gosta mais de ser muleta!",
            "likes": 5,
            "hasReplies": false,
            "numberOfReplies": 0,
            "replies": []
        },
        {
            "id": "5206902962",
            "user": "bolideirayahoocombr",
            "date": "5 days ago",
            "timestamp": "NA",
            "commentText": "O Punjab pode dormir descansado e roncar porque o Rui Rio não sabe fazer oposição e não faz o PSD crescer!!!<br/>E ainda por cima  anda preocupado com o crescimento do Chega!!! Burro da meerda!!",
            "likes": 4,
            "hasReplies": true,
            "numberOfReplies": 1,
            "replies": [
                {
                    "id": "5207071323",
                    "user": "disqus_LerI7mwknD",
                    "date": "5 days ago",
                    "timestamp": "NA",
                    "commentText": "O PS está confortável por muleta do PR.",
                    "likes": 0,
                    "hasReplies": false,
                    "numberOfReplies": 0,
                    "replies": []
                }
            ]
        },
        {
            "id": "5206856381",
            "user": "bolideirayahoocombr",
            "date": "5 days ago",
            "timestamp": "NA",
            "commentText": "Ora, temos o burrinho Rui Rio preocupado com o crescimento do Chega!!! Vejam bem!!!! Parece impossível!!! Que anjinho!!<br/>E com a ultima sondagem do PS nos 40,3% não fica preocupado!?<br/>Rui Rio tem de ir dar banho ao cão e lavar-se a seguir na mesma água!!!",
            "likes": 4,
            "hasReplies": false,
            "numberOfReplies": 0,
            "replies": []
        },
        {
            "id": "5206833459",
            "user": "disqus_rAIpRKQqXo",
            "date": "5 days ago",
            "timestamp": "NA",
            "commentText": "Este parece mais preocupado com a votação do CHEGA do que com a do PS. <br/>Disse \"\"Será mau se o líder do Chega tiver uma votação grande e expressiva\"\" mas pensou \"\"Será mau  para mim se o líder do Chega tiver uma votação grande e expressiva\"\"",
            "likes": 7,
            "hasReplies": true,
            "numberOfReplies": 1,
            "replies": [
                {
                    "id": "5206834781",
                    "user": "bolideirayahoocombr",
                    "date": "5 days ago",
                    "timestamp": "NA",
                    "commentText": "Rui Rio politicamente é um burro! Dizer esta tonteira!!! Deveria dizer se o PS tiver grande votação é que é uma preocupação!!!",
                    "likes": 4,
                    "hasReplies": false,
                    "numberOfReplies": 0,
                    "replies": []
                }
            ]
        },
        {
            "id": "5206820991",
            "user": "bolideirayahoocombr",
            "date": "5 days ago",
            "timestamp": "NA",
            "commentText": "Rui Rio só diz besteiras e tonteiras!!!",
            "likes": 4,
            "hasReplies": false,
            "numberOfReplies": 0,
            "replies": []
        },
        {
            "id": "5206813982",
            "user": "bolideirayahoocombr",
            "date": "5 days ago",
            "timestamp": "NA",
            "commentText": "Rui Rio é sério, honesto e impoluto. Mas é só isso.... Não sabe fazer oposição ao manhoso e matreiro Costa.<br/>Sondagens PS 40,3% depois deste descalabro económico!!! TAP, NB etc.<br/>                    PSD 28,5%!!!! Quer mais!? Óh Rui Rio atira-te ao rio!!!!<br/>Voto Chega porque é o único politico com eles no sitio!!!",
            "likes": 4,
            "hasReplies": true,
            "numberOfReplies": 9,
            "replies": [
                {
                    "id": "5206822348",
                    "user": "disqus_IsbArl2mJt",
                    "date": "5 days ago",
                    "timestamp": "NA",
                    "commentText": "Ser sério e honesto é uma raridade, nos dias de hoje. E, na política, mais raridade é. A Rui Rio, falta o resto.",
                    "likes": 1,
                    "hasReplies": true,
                    "numberOfReplies": 8,
                    "replies": [
                        {
                            "id": "5206825415",
                            "user": "bolideirayahoocombr",
                            "date": "5 days ago",
                            "timestamp": "NA",
                            "commentText": "Pois claro! É uma batata como politico astuto!!!",
                            "likes": 1,
                            "hasReplies": true,
                            "numberOfReplies": 7,
                            "replies": [
                                {
                                    "id": "5206828923",
                                    "user": "disqus_IsbArl2mJt",
                                    "date": "5 days ago",
                                    "timestamp": "NA",
                                    "commentText": "Se a seriedade e honestidade desse vitórias eleitorais..........mas não dá.",
                                    "likes": 1,
                                    "hasReplies": true,
                                    "numberOfReplies": 6,
                                    "replies": [
                                        {
                                            "id": "5206832782",
                                            "user": "bolideirayahoocombr",
                                            "date": "5 days ago",
                                            "timestamp": "NA",
                                            "commentText": "Para ganhar torna-se necessário enganar e vender bem a banha da cobra! Que é o que a maioria do pessoal portuga gosta!!!",
                                            "likes": 2,
                                            "hasReplies": true,
                                            "numberOfReplies": 5,
                                            "replies": [
                                                {
                                                    "id": "5206834120",
                                                    "user": "disqus_IsbArl2mJt",
                                                    "date": "5 days ago",
                                                    "timestamp": "NA",
                                                    "commentText": "Os portugueses não confiam em quem não os engana. Preferem votar em quem os engana.",
                                                    "likes": 2,
                                                    "hasReplies": true,
                                                    "numberOfReplies": 4,
                                                    "replies": [
                                                        {
                                                            "id": "5206836100",
                                                            "user": "bolideirayahoocombr",
                                                            "date": "5 days ago",
                                                            "timestamp": "NA",
                                                            "commentText": "Precisamente! Os Portugueses gostam de quem lhes prometa o céu na terra!",
                                                            "likes": 1,
                                                            "hasReplies": true,
                                                            "numberOfReplies": 3,
                                                            "replies": [
                                                                {
                                                                    "id": "5207370011",
                                                                    "user": "mjferro",
                                                                    "date": "5 days ago",
                                                                    "timestamp": "NA",
                                                                    "commentText": "Se o voto fosse obrigatório faria deste povo acéfalo gente mais responsável e garantidamente o cenário político seria muito diferente, contrariamente ao que estes partidos manhosos e trapaceiros apregoam que nada mudaria e que em democracia há liberdade mas para cavalgaduras não passa de libertinagem! Manter os mais altos níveis de iliteracia  é o objetivo destes impostores que nos governam!",
                                                                    "likes": 0,
                                                                    "hasReplies": false,
                                                                    "numberOfReplies": 0,
                                                                    "replies": []
                                                                },
                                                                {
                                                                    "id": "5206837871",
                                                                    "user": "disqus_IsbArl2mJt",
                                                                    "date": "5 days ago",
                                                                    "timestamp": "NA",
                                                                    "commentText": "Isso mesmo. E o resultado está à vista: Portugal a caminho de ser o país mais pobre da Europa. Já não falta muito.",
                                                                    "likes": 1,
                                                                    "hasReplies": true,
                                                                    "numberOfReplies": 1,
                                                                    "replies": [
                                                                        {
                                                                            "id": "5206843584",
                                                                            "user": "bolideirayahoocombr",
                                                                            "date": "5 days ago",
                                                                            "timestamp": "NA",
                                                                            "commentText": "Perdeu 5 lugares ultimamente!!! O manhoso Costa não descansa enquanto não colocar Portugal em 27º lugar na UE ou seja o último!!! A lanterna Vermelha!!!!",
                                                                            "likes": 1,
                                                                            "hasReplies": false,
                                                                            "numberOfReplies": 0,
                                                                            "replies": []
                                                                        }
                                                                    ]
                                                                }
                                                            ]
                                                        }
                                                    ]
                                                }
                                            ]
                                        }
                                    ]
                                }
                            ]
                        }
                    ]
                }
            ]
        },
        {
            "id": "5206810374",
            "user": "disqus_pp8bsi2hnJ",
            "date": "5 days ago",
            "timestamp": "NA",
            "commentText": "Ohhh Rio, não te enterres mais!",
            "likes": 7,
            "hasReplies": true,
            "numberOfReplies": 2,
            "replies": [
                {
                    "id": "5206962217",
                    "user": "aquariustranslucido",
                    "date": "5 days ago",
                    "timestamp": "NA",
                    "commentText": "\"afundar\" penso que é  o termo mais correcto...",
                    "likes": 1,
                    "hasReplies": true,
                    "numberOfReplies": 1,
                    "replies": [
                        {
                            "id": "5207166071",
                            "user": "disqus_pp8bsi2hnJ",
                            "date": "5 days ago",
                            "timestamp": "NA",
                            "commentText": "Terra ou água,,,com a primeira fica enterrado, com a segunda afoga-se.<br/> Vai tudo dar ao mesmo.",
                            "likes": 2,
                            "hasReplies": false,
                            "numberOfReplies": 0,
                            "replies": []
                        }
                    ]
                }
            ]
        },
        {
            "id": "5206809476",
            "user": "bolideirayahoocombr",
            "date": "5 days ago",
            "timestamp": "NA",
            "commentText": "\"Será mau se o líder do Chega tiver uma votação grande e expressiva\", aponta Rui Rio!<br/>E porquê André Ventura tem grande votação? Porque o Rui Riacho não sabe fazer oposição!!!<br/>Parece um C0na Mole... Um bengaleiro.....É isso, e o Rui Rio não se apercebe e não vê!!!!!",
            "likes": 2,
            "hasReplies": false,
            "numberOfReplies": 0,
            "replies": []
        },
        {
            "id": "5206800944",
            "user": "disqus_IsbArl2mJt",
            "date": "5 days ago",
            "timestamp": "NA",
            "commentText": "Caro Rui Rio. Pode ficar descansado que Ventura vai ter votação expressiva e, provavelmente, mais expressiva do que muitos pensam. E a culpa é dos partidos do sistema, especialmente do PS e do PSD, que se apoderaram da Democracia, das instituições, do Estado, das empresas públicas e da Justiça.",
            "likes": 5,
            "hasReplies": false,
            "numberOfReplies": 0,
            "replies": []
        },
        {
            "id": "5206784219",
            "user": "disqus_NDONqXPlqF",
            "date": "5 days ago",
            "timestamp": "NA",
            "commentText": "Cidadãos Portugueses, esqueçam a corja neoliberal, clerical, anti-republica, e anti-nacional, representada pela facção derrotada de Pedro Coelho.\nHoje, os Portugueses voltam a ter uma alternativa, chama-se Rui Rio assim como o Partido Social Democrata (PSD) por si liderado, ambos são os legítimos representantes da República, dos cidadãos Portugueses, e do Interesse Nacional.\nPortugal, por culpa da passividade e da incompetência, foi transformado num protectorado de uma Europa sem coragem de se autoconstruir, afundada no Relativismo e rejeitando Princípios, Valores e Ideologias.\nEstá assim comprometido o Interesse Nacional e o Bem Comum dos Portugueses.\nTambém a posse das máquinas informativas pelos poderes aqui denunciados, ajuda a convencer os Portugueses de que não há outro caminho de Regeneração, de Democracia e de Desenvolvimento Integral da Pátria, a não ser o deste percurso de “apagada e vil tristeza” por onde nos forçam os “velhos do Restelo” do século XXI português.\nOs socialmente mais débeis são os mais covardemente atingidos e sofredores, porque assim o escolheram as oligarquias e as sociedade secretas.\nA crise tinha de ser enfrentada, mas não desta maneira de genocídio social\nFonte: «A Tomada da Bastilha» - Alberto João Jardim",
            "likes": 0,
            "hasReplies": false,
            "numberOfReplies": 0,
            "replies": []
        },
        {
            "id": "5206719404",
            "user": "Disqusmanuelgomes",
            "date": "5 days ago",
            "timestamp": "NA",
            "commentText": "Mau é o candidato apoiado pela direita ter votação expressiva quando traídos da mesma : o hipocritamente Marcello .\nDois todos uns arregimentados traindo o povo pelo sistema .\nEssa é a vergonha ausência da oposição mas conluio até frasquikho exemplo disso\nPrepara as malas Rio já tiveste a oportunidade ser oposição e alternativa .\nEstá a passar a oportunidade vais de vela na próxima oportunidade .",
            "likes": 1,
            "hasReplies": true,
            "numberOfReplies": 1,
            "replies": [
                {
                    "id": "5206724625",
                    "user": "Disqusmanuelgomes",
                    "date": "5 days ago",
                    "timestamp": "NA",
                    "commentText": "São uns lorpas . Apoiam Marcelo . O hipocrita",
                    "likes": 0,
                    "hasReplies": false,
                    "numberOfReplies": 0,
                    "replies": []
                }
            ]
        },
        {
            "id": "5206713647",
            "user": "ruikkrull",
            "date": "5 days ago",
            "timestamp": "NA",
            "commentText": "Ai que lá se vai a iníqua CONSTITUIÇÃO do aleijadinho estrutural bocal que permite o COMUNIMUS e seus  fantasmas os símbolos ASSASSINOS do século passado e das patifarias da CULTURA DE MORTE da LEI DO ABORTO e da futura (?) EUTÁNÁSIA. e o número de indigentes da MAMADEIRA da AR",
            "likes": 0,
            "hasReplies": false,
            "numberOfReplies": 0,
            "replies": []
        },
        {
            "id": "5206704310",
            "user": "disqus_D1QkCg2wwK",
            "date": "5 days ago",
            "timestamp": "NA",
            "commentText": "caros jornaleiros do SOL.<br/>lamento informar que o povo não é tão ignorante como pensam... eu sei que é giro brincar com a posição de manchets, titutlos, subtitulos...mas por vezes é também irresponsavel e/ou apenas mentiroso\nisto: «Rui Rio foi ainda questionado sobre se preferia ver Ana Gomes ou André Ventura em segundo lugar nas presidenciais, mas recusou-se a responder»<br/>é muito diferente disto:  «\"Será mau se o líder do Chega tiver uma votação grande e expressiva\", aponta Rui Rio<br/>Rui Rio foi ainda questionado sobre se preferia ver Ana Gomes ou André Ventura em segundo lugar nas presidenciais»",
            "likes": 1,
            "hasReplies": false,
            "numberOfReplies": 0,
            "replies": []
        },
        {
            "id": "5206703454",
            "user": "disqus_EdPJc532K3",
            "date": "5 days ago",
            "timestamp": "NA",
            "commentText": "Dá lhe André eles até tremem.",
            "likes": 4,
            "hasReplies": false,
            "numberOfReplies": 0,
            "replies": []
        },
        {
            "id": "5206697034",
            "user": "relvas_analytics",
            "date": "5 days ago",
            "timestamp": "NA",
            "commentText": "...o estúpido Rio legitimou o Chega quando permitiu uma coligação nos Açores e deu a entender que não se opunha a uma coligação nacional nas legislativas, portanto não se pode queixar que muitos dos votos do PSD sejam papados pelo Chega, ele é que se pôs a jeito!<br/>Esta pseudo direitalha burra que se diz ser da direita democrática (que não entendo bem o que é que isso quer dizer) não aprendeu nada com o que se passou em outros países da Europa e do resto do mundo, vão ser papados como os outros foram e a direita vai tornar-se cada vez mais pequena e mas mais radical.",
            "likes": 0,
            "hasReplies": false,
            "numberOfReplies": 0,
            "replies": []
        },
        {
            "id": "5206684324",
            "user": "disqus_1A1JOLwlyE",
            "date": "5 days ago",
            "timestamp": "NA",
            "commentText": "És grande Ventura.",
            "likes": 7,
            "hasReplies": true,
            "numberOfReplies": 1,
            "replies": [
                {
                    "id": "5206694873",
                    "user": "ruikkrull",
                    "date": "5 days ago",
                    "timestamp": "NA",
                    "commentText": "MESMO, sem necessitar das LESMAS e ALFORRECAS do regime.<br/> Como é lindo ver o focinho daquelas pacóvias cientistas de doméstico dedinho no ass  CUnfinado até ao Esgoto Oral Spooky wooky at a distance a grunhirem da fístula.",
                    "likes": 2,
                    "hasReplies": false,
                    "numberOfReplies": 0,
                    "replies": []
                }
            ]
        },
        {
            "id": "5206682225",
            "user": "TopoTudo",
            "date": "5 days ago",
            "timestamp": "NA",
            "commentText": "Cada vez mais o PS afirma-se como partido Social Democrata, depois de por no bolso a comunada e manter quieto o Bloco das meninas da Linha do Estoril..",
            "likes": 1,
            "hasReplies": false,
            "numberOfReplies": 0,
            "replies": []
        },
        {
            "id": "5206681354",
            "user": "disqus_HVgeFFuj93",
            "date": "5 days ago",
            "timestamp": "NA",
            "commentText": "Eu voto no André Ventura 👍.\nVoto no CHEGA e o Rui Rio anda borrado de medo que o CHEGA venha a ultrapassar o PSD.",
            "likes": 6,
            "hasReplies": true,
            "numberOfReplies": 1,
            "replies": [
                {
                    "id": "5206702664",
                    "user": "ruikkrull",
                    "date": "5 days ago",
                    "timestamp": "NA",
                    "commentText": "IDEM IBIDEM!<br/>Cá em casa todos bem e também.",
                    "likes": 1,
                    "hasReplies": false,
                    "numberOfReplies": 0,
                    "replies": []
                }
            ]
        },
        {
            "id": "5206679744",
            "user": "TopoTudo",
            "date": "5 days ago",
            "timestamp": "NA",
            "commentText": "Bom, o CDS vai desaparecer. O PSD tende a ficar próximo do antigo CDS. As coias estão a compor-se para o ...PS.",
            "likes": 0,
            "hasReplies": true,
            "numberOfReplies": 1,
            "replies": [
                {
                    "id": "5206685793",
                    "user": "ssthunder",
                    "date": "5 days ago",
                    "timestamp": "NA",
                    "commentText": "ainda o pcp vai desaparecer primeiro",
                    "likes": 0,
                    "hasReplies": false,
                    "numberOfReplies": 0,
                    "replies": []
                }
            ]
        },
        {
            "id": "5206673544",
            "user": "ruikkrull",
            "date": "5 days ago",
            "timestamp": "NA",
            "commentText": "QUE PACÓVIA IDIOTICE!!! + DESCABELADA!!!.<br/>Alguém quer saber que tipo de fofinho papel higiénico ele usa para limpar o ASS se não for os dedos e posteriormente a parede.",
            "likes": 0,
            "hasReplies": false,
            "numberOfReplies": 0,
            "replies": []
        },
        {
            "id": "5206673443",
            "user": "disqus_1A1JOLwlyE",
            "date": "5 days ago",
            "timestamp": "NA",
            "commentText": "Força André Ventura eu estou contigo.",
            "likes": 8,
            "hasReplies": true,
            "numberOfReplies": 4,
            "replies": [
                {
                    "id": "5206680821",
                    "user": "bigcurak",
                    "date": "5 days ago",
                    "timestamp": "NA",
                    "commentText": "Isto e a essência do ch@g@. Os tristes comentadores clonam nicks pois não têm para mais.<br/>Os dirigentes disseminam ódio.",
                    "likes": 0,
                    "hasReplies": true,
                    "numberOfReplies": 2,
                    "replies": [
                        {
                            "id": "5206801798",
                            "user": "Meliodasreidosdemonios",
                            "date": "5 days ago",
                            "timestamp": "NA",
                            "commentText": "Nos inúmeros canais YouTube que essa gente tem (de onde vem o dinheiro que paga isso?), os comentários são do mais burro que há, com apelos à violência pelo meio.",
                            "likes": 1,
                            "hasReplies": true,
                            "numberOfReplies": 1,
                            "replies": [
                                {
                                    "id": "5207108216",
                                    "user": "bigcurak",
                                    "date": "5 days ago",
                                    "timestamp": "NA",
                                    "commentText": "Evidentemente.São apologistas do ódio",
                                    "likes": 1,
                                    "hasReplies": false,
                                    "numberOfReplies": 0,
                                    "replies": []
                                }
                            ]
                        }
                    ]
                },
                {
                    "id": "5206677045",
                    "user": "ruikkrull",
                    "date": "5 days ago",
                    "timestamp": "NA",
                    "commentText": "Todes estames come nas flores.",
                    "likes": 0,
                    "hasReplies": false,
                    "numberOfReplies": 0,
                    "replies": []
                }
            ]
        },
        {
            "id": "5206672046",
            "user": "ssthunder",
            "date": "5 days ago",
            "timestamp": "NA",
            "commentText": "falou a p do monhé",
            "likes": 0,
            "hasReplies": false,
            "numberOfReplies": 0,
            "replies": []
        },
        {
            "id": "5206671310",
            "user": "disqus_pyjLUpcSC4",
            "date": "5 days ago",
            "timestamp": "NA",
            "commentText": "Este deveria estar calado e aprender a fazer oposição e o que é democracia. Os votantes do Chega como eu não têm de pedir autorização de ninguém.",
            "likes": 3,
            "hasReplies": false,
            "numberOfReplies": 0,
            "replies": []
        },
        {
            "id": "5206669602",
            "user": "bigcurak",
            "date": "5 days ago",
            "timestamp": "NA",
            "commentText": "Seria mau? Muito pior do que isso .<br/>SERIA UM ATRASO CIVILIZACIONAL",
            "likes": 0,
            "hasReplies": true,
            "numberOfReplies": 1,
            "replies": [
                {
                    "id": "5206674734",
                    "user": "disqus_Bgjgzidp1j",
                    "date": "5 days ago",
                    "timestamp": "NA",
                    "commentText": "já pouca gente vota....é o que nos vale..nas proximas não vou lá, pelo covid",
                    "likes": 0,
                    "hasReplies": false,
                    "numberOfReplies": 0,
                    "replies": []
                }
            ]
        },
        {
            "id": "5206661985",
            "user": "joovascoalexandremouta",
            "date": "5 days ago",
            "timestamp": "NA",
            "commentText": "É mau para o Pais ou mau para ti? Não fosses tao incompetente e o psd estaria à frente das sondagens, agora ser igual ao ps é que nao vais a lado nenhum.",
            "likes": 3,
            "hasReplies": true,
            "numberOfReplies": 2,
            "replies": [
                {
                    "id": "5206679535",
                    "user": "disqus_oQ6NjihhdN",
                    "date": "5 days ago",
                    "timestamp": "NA",
                    "commentText": "O PSD nem com o Chega la vai. É por isso que a esquerda fez uma FP monstruosa! São votos garantidos e essa mesma FP tem medo da direita pois sabe que vai logo perder os  privilégios que estão vedados a quem trabalha no privado! Depois essas pessoas têm familiares que votam na esquerda para que esses privilegios fiquem na familia. A seguir junte os RSI, os que vivem de subsidios, etc. Somos um país de subsidio-dependentes ,alimentados por uma esquerda que tudo fará para que as coisas continuem como estão. A força do PS é a Função Publica e quem é alimentado pelo Orçamento de Estado.",
                    "likes": 1,
                    "hasReplies": false,
                    "numberOfReplies": 0,
                    "replies": []
                },
                {
                    "id": "5206675932",
                    "user": "disqus_Bgjgzidp1j",
                    "date": "5 days ago",
                    "timestamp": "NA",
                    "commentText": "igual ao PS ?...mesmo pouca gente votando o PPD perde por muitos para o PS",
                    "likes": 0,
                    "hasReplies": false,
                    "numberOfReplies": 0,
                    "replies": []
                }
            ]
        },
        {
            "id": "5206661086",
            "user": "domfinley",
            "date": "5 days ago",
            "timestamp": "NA",
            "commentText": "Se os políticos que desgovernaram Portugal nas últimas décadas não fossem incompetentes, ineptos, corruptos, mau carácter e feios, hoje não teriam medo do Ventura ou do Cotrim de Figueiredo. As pessoas estão aos poucos a começar a abrir os olhos após décadas de promessas falhadas. Principalmente os emigrantes que conhecem o mundo, é por isso que muitos já não regressam.",
            "likes": 3,
            "hasReplies": false,
            "numberOfReplies": 0,
            "replies": []
        },
        {
            "id": "5206660191",
            "user": "disqus_HcDh0A1uBQ",
            "date": "5 days ago",
            "timestamp": "NA",
            "commentText": "CHEGA de socialismo e de lambe-botas de socialismo!",
            "likes": 4,
            "hasReplies": false,
            "numberOfReplies": 0,
            "replies": []
        },
        {
            "id": "5206641250",
            "user": "disqus_Zf5nBRQLBe",
            "date": "5 days ago",
            "timestamp": "NA",
            "commentText": "Pronto, mais umas centenas de votos para Ventura com este \"apelo\" de Rio.",
            "likes": 4,
            "hasReplies": true,
            "numberOfReplies": 3,
            "replies": [
                {
                    "id": "5206683915",
                    "user": "disqus_oQ6NjihhdN",
                    "date": "5 days ago",
                    "timestamp": "NA",
                    "commentText": "Acho que o Ventura vai desistir se não puder fazer campanha eleitoral. E se assim acontecer será a maior jogada politica desde 74.",
                    "likes": 0,
                    "hasReplies": true,
                    "numberOfReplies": 2,
                    "replies": [
                        {
                            "id": "5206685468",
                            "user": "bigcurak",
                            "date": "5 days ago",
                            "timestamp": "NA",
                            "commentText": "um demagogo nao fazer demagogia. Nem pense.<br/>O rato do Aldrabe vai a todas",
                            "likes": 0,
                            "hasReplies": true,
                            "numberOfReplies": 1,
                            "replies": [
                                {
                                    "id": "5206752967",
                                    "user": "disqus_oQ6NjihhdN",
                                    "date": "5 days ago",
                                    "timestamp": "NA",
                                    "commentText": "Pense la bem. Se desistir porque  a AR o impede de fazer campanha, ele desiste mas o seu nome e foto ficam no bolhetim de voto!!! Quem quiser votar Ventura, faze-o na mesma! Vai a jogo sem ir e depois dirá que que as Presidenciais foram uma farsa pois não trataram todos por igual! E mais uma coisa. Ficará sempre a saber aquilo que quer pois basta comparar os nulos destas eleições com a ultima eleição presidencial. Se desistir por não poder suspender o seu  mandato de deputado é um golpe de génio que o fará capitalizar muitos votos nas proximas eleições. Penso eu de que!",
                                    "likes": 0,
                                    "hasReplies": false,
                                    "numberOfReplies": 0,
                                    "replies": []
                                }
                            ]
                        }
                    ]
                }
            ]
        },
        {
            "id": "5206637253",
            "user": "disqus_Sy6XUeusza",
            "date": "5 days ago",
            "timestamp": "NA",
            "commentText": "Este não está preocupado com o \"mau mau\" está preocupado é que o AV lhe passe à frente.",
            "likes": 4,
            "hasReplies": false,
            "numberOfReplies": 0,
            "replies": []
        },
        {
            "id": "5206634805",
            "user": "disqus_mogfSPaHQJ",
            "date": "5 days ago",
            "timestamp": "NA",
            "commentText": "Será mau no sentido que será mais uma demonstração do cadáver político que é o sr. Rui Rio...",
            "likes": 5,
            "hasReplies": true,
            "numberOfReplies": 1,
            "replies": [
                {
                    "id": "5206733031",
                    "user": "disqus_aiWRq6UM2Q",
                    "date": "5 days ago",
                    "timestamp": "NA",
                    "commentText": "Em boa parte a subida do chega deve-se à inercia e cumplicidade deste Rui Rio com o governo...este tipo nem sequer é oposição, fez mais guerra ao PCP do que ao PS do governo...Um inútil que vai ter o pior resultado de sempre do PSD nas próximas legislativas... O Rui Rio até combinou com o governo o decreto lei que o Marcelo vetou por abrir as portas, ainda mais, à corrupção...",
                    "likes": 2,
                    "hasReplies": false,
                    "numberOfReplies": 0,
                    "replies": []
                }
            ]
        }
    ]
}
